[{
	"url": "#",
	"active":true,
	"text": "Alerts",
	"children": [{
		"url": "#",
		"active":false,
		"text": "Child link1"
	},
	{
		"url": "#",
		"active":false,
		"text": "Child link2"
	}]
},
{
	"url": "#",
	"active":false,
	"text": "Release Notes"
},
{
	"url": "#",
	"active":false,
	"text": "Transition Roadmap",
	"children": [{
		"url": "#",
		"text": "Child link3"
	},
	{
		"url": "#",
		"active":false,
		"text": "Child link4",
		"children": [{
			"url": "#",
			"text": "Grandchild link5"
		},
		{
			"url": "#",
			"active":false,
			"text": "Grandchild link6"
		},
		{
			"url": "#",
			"active":false,
			"text": "Grandchild link7"
		}]
	}]
}]
